{"meta": {"code": 200, "requestId": "5e6e41aa1a4b0a001b9f1a3a"}, "response": {"suggestedFilters": {"header": "Tap to show:", "filters": [{"name": "Open now", "key": "openNow"}]}, "headerLocation": "Newton", "headerFullLocation": "Newton, Singapore", "headerLocationGranularity": "neighborhood", "totalResults": 22, "suggestedBounds": {"ne": {"lat": 1.3174810045000045, "lng": 103.84341428208539}, "sw": {"lat": 1.3084809954999954, "lng": 103.8344287179146}}, "groups": [{"type": "Recommended Places", "name": "recommended", "items": [{"reasons": {"count": 0, "items": [{"summary": "This spot is popular", "type": "general", "reasonName": "globalInteractionReason"}]}, "venue": {"id": "4ba65051f964a520464539e3", "name": "Hai Yan BBQ Seafood", "location": {"address": "#01-11 Newton Food Centre", "crossStreet": "500 Clemenceau Avenue North", "lat": 1.312084, "lng": 103.8395, "labeledLatLngs": [{"label": "display", "lat": 1.312084, "lng": 103.8395}], "distance": 118, "postalCode": "229495", "cc": "SG", "neighborhood": "Newton", "city": "Singapore", "country": "Singapore", "formattedAddress": ["#01-11 Newton Food Centre (500 Clemenceau Avenue North)", "229495", "Singapore"]}, "categories": [{"id": "4bf58dd8d48988d1ce941735", "name": "Seafood Restaurant", "pluralName": "Seafood Restaurants", "shortName": "Seafood", "icon": {"prefix": "https://ss3.4sqi.net/img/categories_v2/food/seafood_", "suffix": ".png"}, "primary": true}], "photos": {"count": 0, "groups": []}}, "referralId": "e-0-4ba65051f964a520464539e3-0"}, {"reasons": {"count": 0, "items": [{"summary": "This spot is popular", "type": "general", "reasonName": "globalInteractionReason"}]}, "venue": {"id": "5281b8cc11d2ca794e59d920", "name": "Hup Kee Fried Oyster Omelette \u5408\u8a18\u7092\u8814\u714e", "location": {"address": "#01-73 Newton Food Centre, 500 Clemenceau Ave North", "lat": 1.3121870894840317, "lng": 103.83954553084332, "labeledLatLngs": [{"label": "display", "lat": 1.3121870894840317, "lng": 103.83954553084332}], "distance": 112, "postalCode": "229495", "cc": "SG", "neighborhood": "Newton", "city": "Singapore", "country": "Singapore", "formattedAddress": ["#01-73 Newton Food Centre, 500 Clemenceau Ave North", "229495", "Singapore"]}, "categories": [{"id": "4bf58dd8d48988d145941735", "name": "Chinese Restaurant", "pluralName": "Chinese Restaurants", "shortName": "Chinese", "icon": {"prefix": "https://ss3.4sqi.net/img/categories_v2/food/asian_", "suffix": ".png"}, "primary": true}], "photos": {"count": 0, "groups": []}}, "referralId": "e-0-5281b8cc11d2ca794e59d920-1"}, {"reasons": {"count": 0, "items": [{"summary": "This spot is popular", "type": "general", "reasonName": "globalInteractionReason"}]}, "venue": {"id": "4d95ed48647d8cfae4f3ab3d", "name": "Heng Carrot Cake", "location": {"address": "#01-28 Newton Food Centre", "lat": 1.3120799750284224, "lng": 103.83976544798027, "labeledLatLngs": [{"label": "display", "lat": 1.3120799750284224, "lng": 103.83976544798027}], "distance": 137, "cc": "SG", "city": "Singapore", "country": "Singapore", "formattedAddress": ["#01-28 Newton Food Centre", "Singapore"]}, "categories": [{"id": "4bf58dd8d48988d142941735", "name": "Asian Restaurant", "pluralName": "Asian Restaurants", "shortName": "Asian", "icon": {"prefix": "https://ss3.4sqi.net/img/categories_v2/food/asian_", "suffix": ".png"}, "primary": true}], "photos": {"count": 0, "groups": []}}, "referralId": "e-0-4d95ed48647d8cfae4f3ab3d-2"}, {"reasons": {"count": 0, "items": [{"summary": "This spot is popular", "type": "general", "reasonName": "globalInteractionReason"}]}, "venue": {"id": "4b1e7356f964a5201f1a24e3", "name": "Newton Food Centre", "location": {"address": "500 Clemenceau Ave.", "crossStreet": "Newton Food Centre", "lat": 1.3119489901287666, "lng": 103.83956682309288, "labeledLatLngs": [{"label": "display", "lat": 1.3119489901287666, "lng": 103.83956682309288}], "distance": 135, "postalCode": "229495", "cc": "SG", "city": "Singapore", "country": "Singapore", "formattedAddress": ["500 Clemenceau Ave. (Newton Food Centre)", "229495", "Singapore"]}, "categories": [{"id": "4bf58dd8d48988d120951735", "name": "Food Court", "pluralName": "Food Courts", "shortName": "Food Court", "icon": {"prefix": "https://ss3.4sqi.net/img/categories_v2/shops/food_foodcourt_", "suffix": ".png"}, "primary": true}], "photos": {"count": 0, "groups": []}}, "referralId": "e-0-4b1e7356f964a5201f1a24e3-3"}, {"reasons": {"count": 0, "items": [{"summary": "This spot is popular", "type": "general", "reasonName": "globalInteractionReason"}]}, "venue": {"id": "4e78087c887738167d3360df", "name": "Chui Huay Lim Teochew Cuisine", "location": {"address": "#01-02, Chui Huay Lim Club", "crossStreet": "190 Keng Lee Rd.", "lat": 1.3139704597030852, "lng": 103.84154464351671, "labeledLatLngs": [{"label": "display", "lat": 1.3139704597030852, "lng": 103.84154464351671}], "distance": 312, "postalCode": "308409", "cc": "SG", "city": "Singapore", "country": "Singapore", "formattedAddress": ["#01-02, Chui Huay Lim Club (190 Keng Lee Rd.)", "308409", "Singapore"]}, "categories": [{"id": "4bf58dd8d48988d145941735", "name": "Chinese Restaurant", "pluralName": "Chinese Restaurants", "shortName": "Chinese", "icon": {"prefix": "https://ss3.4sqi.net/img/categories_v2/food/asian_", "suffix": ".png"}, "primary": true}], "photos": {"count": 0, "groups": []}}, "referralId": "e-0-4e78087c887738167d3360df-4"}, {"reasons": {"count": 0, "items": [{"summary": "This spot is popular", "type": "general", "reasonName": "globalInteractionReason"}]}, "venue": {"id": "4bf0827917880f47e26b2937", "name": "Lifestyle Fitness", "location": {"address": "5F Sheraton Towers Hotel", "crossStreet": "39 Scotts Rd", "lat": 1.3120017600309841, "lng": 103.83644016148388, "labeledLatLngs": [{"label": "display", "lat": 1.3120017600309841, "lng": 103.83644016148388}], "distance": 296, "cc": "SG", "city": "Singapore", "country": "Singapore", "formattedAddress": ["5F Sheraton Towers Hotel (39 Scotts Rd)", "Singapore"]}, "categories": [{"id": "4bf58dd8d48988d175941735", "name": "Gym / Fitness Center", "pluralName": "Gyms or Fitness Centers", "shortName": "Gym / Fitness", "icon": {"prefix": "https://ss3.4sqi.net/img/categories_v2/building/gym_", "suffix": ".png"}, "primary": true}], "photos": {"count": 0, "groups": []}}, "referralId": "e-0-4bf0827917880f47e26b2937-5"}, {"reasons": {"count": 0, "items": [{"summary": "This spot is popular", "type": "general", "reasonName": "globalInteractionReason"}]}, "venue": {"id": "4be563532468c928c2efff42", "name": "Bangkok Express", "location": {"address": "#01-04 Newton Circus Food Centre", "crossStreet": "Facing public carpark", "lat": 1.311705065994275, "lng": 103.83927866344747, "labeledLatLngs": [{"label": "display", "lat": 1.311705065994275, "lng": 103.83927866344747}], "distance": 147, "cc": "SG", "city": "Singapore", "country": "Singapore", "formattedAddress": ["#01-04 Newton Circus Food Centre (Facing public carpark)", "Singapore"]}, "categories": [{"id": "4bf58dd8d48988d149941735", "name": "Thai Restaurant", "pluralName": "Thai Restaurants", "shortName": "Thai", "icon": {"prefix": "https://ss3.4sqi.net/img/categories_v2/food/thai_", "suffix": ".png"}, "primary": true}], "photos": {"count": 0, "groups": []}}, "referralId": "e-0-4be563532468c928c2efff42-6"}, {"reasons": {"count": 0, "items": [{"summary": "This spot is popular", "type": "general", "reasonName": "globalInteractionReason"}]}, "venue": {"id": "4efa6a36c512f2277b3abccd", "name": "XO Minced Meat Noodle", "location": {"address": "#01-10, Newton Hawker Center", "crossStreet": "500 Clemenceau Avenue North", "lat": 1.3117897358300443, "lng": 103.83949127729245, "labeledLatLngs": [{"label": "display", "lat": 1.3117897358300443, "lng": 103.83949127729245}], "distance": 146, "cc": "SG", "city": "Singapore", "country": "Singapore", "formattedAddress": ["#01-10, Newton Hawker Center (500 Clemenceau Avenue North)", "Singapore"]}, "categories": [{"id": "4bf58dd8d48988d1d1941735", "name": "Noodle House", "pluralName": "Noodle Houses", "shortName": "Noodles", "icon": {"prefix": "https://ss3.4sqi.net/img/categories_v2/food/ramen_", "suffix": ".png"}, "primary": true}], "photos": {"count": 0, "groups": []}}, "referralId": "e-0-4efa6a36c512f2277b3abccd-7"}, {"reasons": {"count": 0, "items": [{"summary": "This spot is popular", "type": "general", "reasonName": "globalInteractionReason"}]}, "venue": {"id": "51f8f230498e9c838f08a0ac", "name": "Cheng Ballet Academy", "location": {"address": "#03-00 Boon Liew Building", "crossStreet": "204 Bukit Timah Road", "lat": 1.31179369528792, "lng": 103.84188185052503, "labeledLatLngs": [{"label": "display", "lat": 1.31179369528792, "lng": 103.84188185052503}], "distance": 354, "postalCode": "229863", "cc": "SG", "country": "Singapore", "formattedAddress": ["#03-00 Boon Liew Building (204 Bukit Timah Road)", "229863", "Singapore"]}, "categories": [{"id": "4bf58dd8d48988d134941735", "name": "Dance Studio", "pluralName": "Dance Studios", "shortName": "Dance Studio", "icon": {"prefix": "https://ss3.4sqi.net/img/categories_v2/arts_entertainment/performingarts_dancestudio_", "suffix": ".png"}, "primary": true}], "photos": {"count": 0, "groups": []}}, "referralId": "e-0-51f8f230498e9c838f08a0ac-8"}, {"reasons": {"count": 0, "items": [{"summary": "This spot is popular", "type": "general", "reasonName": "globalInteractionReason"}]}, "venue": {"id": "4b05880bf964a520c1ad22e3", "name": "Sheraton Towers Singapore", "location": {"address": "39 Scotts Rd", "lat": 1.3118244335501041, "lng": 103.83647605765873, "labeledLatLngs": [{"label": "display", "lat": 1.3118244335501041, "lng": 103.83647605765873}], "distance": 301, "postalCode": "228230", "cc": "SG", "city": "Singapore", "state": "SG-01", "country": "Singapore", "formattedAddress": ["39 Scotts Rd", "228230", "Singapore"]}, "categories": [{"id": "4bf58dd8d48988d1fa931735", "name": "Hotel", "pluralName": "Hotels", "shortName": "Hotel", "icon": {"prefix": "https://ss3.4sqi.net/img/categories_v2/travel/hotel_", "suffix": ".png"}, "primary": true}], "photos": {"count": 0, "groups": []}}, "referralId": "e-0-4b05880bf964a520c1ad22e3-9"}, {"reasons": {"count": 0, "items": [{"summary": "This spot is popular", "type": "general", "reasonName": "globalInteractionReason"}]}, "venue": {"id": "4c0e5625d64c0f47f3f9275d", "name": "7-Eleven", "location": {"address": "#B1-01 Newton MRT Station", "crossStreet": "49 Scotts Rd.", "lat": 1.312176173538034, "lng": 103.83811646477324, "labeledLatLngs": [{"label": "display", "lat": 1.312176173538034, "lng": 103.83811646477324}], "distance": 126, "postalCode": "228234", "cc": "SG", "neighborhood": "Newton", "city": "Singapore", "country": "Singapore", "formattedAddress": ["#B1-01 Newton MRT Station (49 Scotts Rd.)", "228234", "Singapore"]}, "categories": [{"id": "4d954b0ea243a5684a65b473", "name": "Convenience Store", "pluralName": "Convenience Stores", "shortName": "Convenience Store", "icon": {"prefix": "https://ss3.4sqi.net/img/categories_v2/shops/conveniencestore_", "suffix": ".png"}, "primary": true}], "photos": {"count": 0, "groups": []}}, "referralId": "e-0-4c0e5625d64c0f47f3f9275d-10"}, {"reasons": {"count": 0, "items": [{"summary": "This spot is popular", "type": "general", "reasonName": "globalInteractionReason"}]}, "venue": {"id": "4b058812f964a520b5af22e3", "name": "Li Bai Cantonese Restaurant", "location": {"address": "GF, Sheraton Towers", "crossStreet": "39 Scotts Rd.", "lat": 1.3117025546883803, "lng": 103.83636136098552, "labeledLatLngs": [{"label": "display", "lat": 1.3117025546883803, "lng": 103.83636136098552}], "distance": 318, "postalCode": "228230", "cc": "SG", "city": "Singapore", "country": "Singapore", "formattedAddress": ["GF, Sheraton Towers (39 Scotts Rd.)", "228230", "Singapore"]}, "categories": [{"id": "4bf58dd8d48988d145941735", "name": "Chinese Restaurant", "pluralName": "Chinese Restaurants", "shortName": "Chinese", "icon": {"prefix": "https://ss3.4sqi.net/img/categories_v2/food/asian_", "suffix": ".png"}, "primary": true}], "photos": {"count": 0, "groups": []}}, "referralId": "e-0-4b058812f964a520b5af22e3-11"}, {"reasons": {"count": 0, "items": [{"summary": "This spot is popular", "type": "general", "reasonName": "globalInteractionReason"}]}, "venue": {"id": "4cd8f05d15d8b60c2fa3680e", "name": "\u8cb4\u8208 Kwee Heng", "location": {"address": "#01-13, Newton Food Centre", "crossStreet": "500 Clemenceau Avenue North", "lat": 1.311673496204694, "lng": 103.83948778635084, "labeledLatLngs": [{"label": "display", "lat": 1.311673496204694, "lng": 103.83948778635084}], "distance": 158, "cc": "SG", "city": "Singapore", "country": "Singapore", "formattedAddress": ["#01-13, Newton Food Centre (500 Clemenceau Avenue North)", "Singapore"]}, "categories": [{"id": "4bf58dd8d48988d145941735", "name": "Chinese Restaurant", "pluralName": "Chinese Restaurants", "shortName": "Chinese", "icon": {"prefix": "https://ss3.4sqi.net/img/categories_v2/food/asian_", "suffix": ".png"}, "primary": true}], "photos": {"count": 0, "groups": []}}, "referralId": "e-0-4cd8f05d15d8b60c2fa3680e-12"}, {"reasons": {"count": 0, "items": [{"summary": "This spot is popular", "type": "general", "reasonName": "globalInteractionReason"}]}, "venue": {"id": "4c65e32a8e9120a16d9dd664", "name": "Executive Lounge", "location": {"address": "Sheraton Towers Hotel", "crossStreet": "Scotts Rd.", "lat": 1.3114193694764729, "lng": 103.83671681347228, "labeledLatLngs": [{"label": "display", "lat": 1.3114193694764729, "lng": 103.83671681347228}], "distance": 300, "postalCode": "228230", "cc": "SG", "city": "Singapore", "country": "Singapore", "formattedAddress": ["Sheraton Towers Hotel (Scotts Rd.)", "228230", "Singapore"]}, "categories": [{"id": "4bf58dd8d48988d1d5941735", "name": "Hotel Bar", "pluralName": "Hotel Bars", "shortName": "Hotel Bar", "icon": {"prefix": "https://ss3.4sqi.net/img/categories_v2/travel/hotel_bar_", "suffix": ".png"}, "primary": true}], "photos": {"count": 0, "groups": []}}, "referralId": "e-0-4c65e32a8e9120a16d9dd664-13"}, {"reasons": {"count": 0, "items": [{"summary": "This spot is popular", "type": "general", "reasonName": "globalInteractionReason"}]}, "venue": {"id": "526cede211d27d207adf4e70", "name": "Kushi Japanese Dining Bar", "location": {"address": "#03-01, Hotel Royal", "crossStreet": "36 Newton Road", "lat": 1.3166600282107797, "lng": 103.84149081590266, "labeledLatLngs": [{"label": "display", "lat": 1.3166600282107797, "lng": 103.84149081590266}], "distance": 499, "postalCode": "307964", "cc": "SG", "city": "Singapore", "country": "Singapore", "formattedAddress": ["#03-01, Hotel Royal (36 Newton Road)", "307964", "Singapore"]}, "categories": [{"id": "4bf58dd8d48988d111941735", "name": "Japanese Restaurant", "pluralName": "Japanese Restaurants", "shortName": "Japanese", "icon": {"prefix": "https://ss3.4sqi.net/img/categories_v2/food/japanese_", "suffix": ".png"}, "primary": true}], "photos": {"count": 0, "groups": []}}, "referralId": "e-0-526cede211d27d207adf4e70-14"}, {"reasons": {"count": 0, "items": [{"summary": "This spot is popular", "type": "general", "reasonName": "globalInteractionReason"}]}, "venue": {"id": "51565ab0e4b044dc7195a124", "name": "Ng Ah Sio Bak Kut Teh \u9ec4\u4e9a\u7ec6\u8089\u9aa8\u8336", "location": {"address": "190 Keng Lee Rd #01-03", "crossStreet": "Chui Huay Lim Club", "lat": 1.3136553111943112, "lng": 103.84147819091777, "labeledLatLngs": [{"label": "display", "lat": 1.3136553111943112, "lng": 103.84147819091777}], "distance": 294, "postalCode": "308409", "cc": "SG", "city": "Singapore", "country": "Singapore", "formattedAddress": ["190 Keng Lee Rd #01-03 (Chui Huay Lim Club)", "308409", "Singapore"]}, "categories": [{"id": "4bf58dd8d48988d145941735", "name": "Chinese Restaurant", "pluralName": "Chinese Restaurants", "shortName": "Chinese", "icon": {"prefix": "https://ss3.4sqi.net/img/categories_v2/food/asian_", "suffix": ".png"}, "primary": true}], "photos": {"count": 0, "groups": []}}, "referralId": "e-0-51565ab0e4b044dc7195a124-15"}, {"reasons": {"count": 0, "items": [{"summary": "This spot is popular", "type": "general", "reasonName": "globalInteractionReason"}]}, "venue": {"id": "4cb9998b4c60a093ac9b40ca", "name": "Lucky Newton Seafood Stall 82", "location": {"address": "Newton Circus Hawker Centre", "lat": 1.3120015190925982, "lng": 103.83968257170125, "labeledLatLngs": [{"label": "display", "lat": 1.3120015190925982, "lng": 103.83968257170125}], "distance": 138, "cc": "SG", "country": "Singapore", "formattedAddress": ["Newton Circus Hawker Centre", "Singapore"]}, "categories": [{"id": "4bf58dd8d48988d1ce941735", "name": "Seafood Restaurant", "pluralName": "Seafood Restaurants", "shortName": "Seafood", "icon": {"prefix": "https://ss3.4sqi.net/img/categories_v2/food/seafood_", "suffix": ".png"}, "primary": true}], "photos": {"count": 0, "groups": []}}, "referralId": "e-0-4cb9998b4c60a093ac9b40ca-16"}, {"reasons": {"count": 0, "items": [{"summary": "This spot is popular", "type": "general", "reasonName": "globalInteractionReason"}]}, "venue": {"id": "4dbb952b4b222080d37cadb0", "name": "Sheraton Towers Poolside", "location": {"address": "5th floor of Sheraton Towers", "lat": 1.3120175636629408, "lng": 103.83637347501903, "labeledLatLngs": [{"label": "display", "lat": 1.3120175636629408, "lng": 103.83637347501903}], "distance": 303, "postalCode": "228230", "cc": "SG", "city": "Singapore", "country": "Singapore", "formattedAddress": ["5th floor of Sheraton Towers", "228230", "Singapore"]}, "categories": [{"id": "4bf58dd8d48988d15e941735", "name": "Pool", "pluralName": "Pools", "shortName": "Pool", "icon": {"prefix": "https://ss3.4sqi.net/img/categories_v2/parks_outdoors/pool_", "suffix": ".png"}, "primary": true}], "photos": {"count": 0, "groups": []}}, "referralId": "e-0-4dbb952b4b222080d37cadb0-17"}, {"reasons": {"count": 0, "items": [{"summary": "This spot is popular", "type": "general", "reasonName": "globalInteractionReason"}]}, "venue": {"id": "4ea50bab7ee52a35ddfa3d24", "name": "Lobby Bar", "location": {"address": "Sheraton Towers Singapore", "crossStreet": "39 Scotts Rd", "lat": 1.3116623110823689, "lng": 103.83641989767955, "labeledLatLngs": [{"label": "display", "lat": 1.3116623110823689, "lng": 103.83641989767955}], "distance": 314, "postalCode": "228230", "cc": "SG", "city": "Singapore", "country": "Singapore", "formattedAddress": ["Sheraton Towers Singapore (39 Scotts Rd)", "228230", "Singapore"]}, "categories": [{"id": "4bf58dd8d48988d1d5941735", "name": "Hotel Bar", "pluralName": "Hotel Bars", "shortName": "Hotel Bar", "icon": {"prefix": "https://ss3.4sqi.net/img/categories_v2/travel/hotel_bar_", "suffix": ".png"}, "primary": true}], "photos": {"count": 0, "groups": []}}, "referralId": "e-0-4ea50bab7ee52a35ddfa3d24-18"}, {"reasons": {"count": 0, "items": [{"summary": "This spot is popular", "type": "general", "reasonName": "globalInteractionReason"}]}, "venue": {"id": "4ed8baa4f5b921398695f5e2", "name": "Skyve Wine Bistro", "location": {"address": "10 Winstedt Rd.", "crossStreet": "Block E #01-17", "lat": 1.3102660895356637, "lng": 103.84169130434049, "labeledLatLngs": [{"label": "display", "lat": 1.3102660895356637, "lng": 103.84169130434049}], "distance": 431, "postalCode": "227977", "cc": "SG", "city": "Singapore", "country": "Singapore", "formattedAddress": ["10 Winstedt Rd. (Block E #01-17)", "227977", "Singapore"]}, "categories": [{"id": "4bf58dd8d48988d123941735", "name": "Wine Bar", "pluralName": "Wine Bars", "shortName": "Wine Bar", "icon": {"prefix": "https://ss3.4sqi.net/img/categories_v2/food/winery_", "suffix": ".png"}, "primary": true}], "photos": {"count": 0, "groups": []}}, "referralId": "e-0-4ed8baa4f5b921398695f5e2-19"}, {"reasons": {"count": 0, "items": [{"summary": "This spot is popular", "type": "general", "reasonName": "globalInteractionReason"}]}, "venue": {"id": "4cfdfa24dccef04d6a44c89c", "name": "INDOCAFE the white house", "location": {"address": "35/35A Scotts Rd", "lat": 1.3110351767920387, "lng": 103.83570045232773, "labeledLatLngs": [{"label": "display", "lat": 1.3110351767920387, "lng": 103.83570045232773}], "distance": 418, "postalCode": "228227", "cc": "SG", "city": "Singapore", "country": "Singapore", "formattedAddress": ["35/35A Scotts Rd", "228227", "Singapore"]}, "categories": [{"id": "4bf58dd8d48988d16d941735", "name": "Caf\u00e9", "pluralName": "Caf\u00e9s", "shortName": "Caf\u00e9", "icon": {"prefix": "https://ss3.4sqi.net/img/categories_v2/food/cafe_", "suffix": ".png"}, "primary": true}], "photos": {"count": 0, "groups": []}}, "referralId": "e-0-4cfdfa24dccef04d6a44c89c-20"}, {"reasons": {"count": 0, "items": [{"summary": "This spot is popular", "type": "general", "reasonName": "globalInteractionReason"}]}, "venue": {"id": "4b058811f964a520a5af22e3", "name": "DOMVS by Gabriel Fratini", "location": {"address": "39 Scotts Road", "crossStreet": "Sheraton Towers", "lat": 1.3119672195158765, "lng": 103.83648284085645, "labeledLatLngs": [{"label": "display", "lat": 1.3119672195158765, "lng": 103.83648284085645}], "distance": 293, "postalCode": "228230", "cc": "SG", "city": "Singapore", "country": "Singapore", "formattedAddress": ["39 Scotts Road (Sheraton Towers)", "228230", "Singapore"]}, "categories": [{"id": "4bf58dd8d48988d110941735", "name": "Italian Restaurant", "pluralName": "Italian Restaurants", "shortName": "Italian", "icon": {"prefix": "https://ss3.4sqi.net/img/categories_v2/food/italian_", "suffix": ".png"}, "primary": true}], "photos": {"count": 0, "groups": []}}, "referralId": "e-0-4b058811f964a520a5af22e3-21"}]}]}}